ni/datastore/__init__.py
ni/datastore/data/__init__.py
ni/datastore/data/_data_store_client.py
ni/datastore/data/_grpc_conversion.py
ni/datastore/data/_types/__init__.py
ni/datastore/data/_types/_error_information.py
ni/datastore/data/_types/_moniker.py
ni/datastore/data/_types/_outcome.py
ni/datastore/data/_types/_published_condition.py
ni/datastore/data/_types/_published_measurement.py
ni/datastore/data/_types/_step.py
ni/datastore/data/_types/_test_result.py
ni/datastore/data/_types/py.typed
ni/datastore/data/py.typed
ni/datastore/metadata/__init__.py
ni/datastore/metadata/_grpc_conversion.py
ni/datastore/metadata/_metadata_store_client.py
ni/datastore/metadata/_types/__init__.py
ni/datastore/metadata/_types/_alias.py
ni/datastore/metadata/_types/_alias_target_type.py
ni/datastore/metadata/_types/_extension_schema.py
ni/datastore/metadata/_types/_hardware_item.py
ni/datastore/metadata/_types/_metadata_items.py
ni/datastore/metadata/_types/_operator.py
ni/datastore/metadata/_types/_software_item.py
ni/datastore/metadata/_types/_test.py
ni/datastore/metadata/_types/_test_adapter.py
ni/datastore/metadata/_types/_test_description.py
ni/datastore/metadata/_types/_test_station.py
ni/datastore/metadata/_types/_uut.py
ni/datastore/metadata/_types/_uut_instance.py
ni/datastore/metadata/_types/py.typed
ni/datastore/metadata/py.typed
ni/datastore/py.typed
ni_datastore-1.0.0.dist-info/LICENSE
ni_datastore-1.0.0.dist-info/METADATA
ni_datastore-1.0.0.dist-info/WHEEL
ni_datastore-1.0.0.dist-info/RECORD
