Metadata-Version: 2.3
Name: ni.datastore
Version: 1.0.0
Summary: APIs for publishing and retrieving data from NI Measurement Data Services
License: MIT
Keywords: datastore
Author: NI
Author-email: opensource@ni.com
Maintainer: Johann Scholtz
Maintainer-email: johann.scholtz@emerson.com
Requires-Python: >=3.10,<4.0
Classifier: Development Status :: 5 - Production/Stable
Classifier: Intended Audience :: Developers
Classifier: Intended Audience :: Manufacturing
Classifier: Intended Audience :: Science/Research
Classifier: License :: OSI Approved :: MIT License
Classifier: Operating System :: Microsoft :: Windows
Classifier: Operating System :: POSIX
Classifier: Programming Language :: Python :: 3
Classifier: Programming Language :: Python :: 3.10
Classifier: Programming Language :: Python :: 3.11
Classifier: Programming Language :: Python :: 3.12
Classifier: Programming Language :: Python :: 3.13
Classifier: Programming Language :: Python :: 3.14
Classifier: Programming Language :: Python :: Implementation :: CPython
Requires-Dist: hightime (>=1.0.0)
Requires-Dist: ni-datamonikers-v1-client (>=1.0.0)
Requires-Dist: ni-measurements-data-v1-client (>=1.0.0)
Requires-Dist: ni-measurements-metadata-v1-client (>=1.0.0)
Requires-Dist: ni-protobuf-types (>=1.1.0)
Requires-Dist: protobuf (>=4.21)
Project-URL: Documentation, https://datastorepython.readthedocs.io/en/latest/
Project-URL: Repository, https://github.com/ni/datastore-python
